LICENSE
metriculous/__init__.py
metriculous/__init___import_star_test.py
metriculous/__init___test.py
metriculous/_comparison.py
metriculous/_comparison_test.py
metriculous/_evaluation.py
metriculous/_evaluation_test.py
metriculous/evaluators/__init__.py
metriculous/evaluators/_bokeh_utils.py
metriculous/evaluators/_bokeh_utils_test.py
metriculous/evaluators/_classification_evaluator.py
metriculous/evaluators/_classification_evaluator_test.py
metriculous/evaluators/_classification_figures_bokeh.py
metriculous/evaluators/_classification_figures_bokeh_test.py
metriculous/evaluators/_classification_utils.py
metriculous/evaluators/_classification_utils_test.py
metriculous/evaluators/_regression_evaluator.py
metriculous/evaluators/_regression_evaluator_test.py
metriculous/evaluators/_regression_figures_bokeh.py
metriculous/evaluators/_regression_utils.py
metriculous/evaluators/_segmentation_evaluator.py
metriculous/evaluators/_segmentation_evaluator_test.py
metriculous/evaluators/_segmentation_figures_bokeh.py
metriculous/metrics.py
metriculous/metrics_test.py
metriculous/test_resources.py
metriculous/utilities.py
metriculous/utilities_test.py
metriculous-0.3.0.dist-info/LICENSE
metriculous-0.3.0.dist-info/WHEEL
metriculous-0.3.0.dist-info/METADATA
metriculous-0.3.0.dist-info/RECORD
