Metadata-Version: 2.1
Name: metriculous
Version: 0.3.0
Summary: Very unstable library containing utilities to measure and visualize statistical properties of machine learning models.
Home-page: https://github.com/metriculous-ml/metriculous
License: MIT
Keywords: metriculous,machine,learning,metrics,statistics,data science,evaluation,regression,classification,residual plot,ROC curve,PR curve,confusion matrix,statistical performance,ML,deep learning,scikit-learn,bokeh,forecasting
Author: Marlon
Maintainer: Marlon
Requires-Python: >=3.7,<4.0
Classifier: Development Status :: 3 - Alpha
Classifier: Intended Audience :: Developers
Classifier: Intended Audience :: Science/Research
Classifier: License :: OSI Approved :: MIT License
Classifier: Programming Language :: Python :: 3
Classifier: Programming Language :: Python :: 3.7
Classifier: Programming Language :: Python :: 3.8
Classifier: Programming Language :: Python :: 3.9
Classifier: Topic :: Scientific/Engineering :: Artificial Intelligence
Classifier: Topic :: Scientific/Engineering :: Bio-Informatics
Classifier: Topic :: Scientific/Engineering :: Information Analysis
Classifier: Topic :: Scientific/Engineering :: Visualization
Classifier: Topic :: Software Development
Classifier: Topic :: Software Development :: Libraries :: Python Modules
Classifier: Topic :: Software Development :: Quality Assurance
Requires-Dist: assertpy (>=0.14.0)
Requires-Dist: bokeh (>=2.1.1,<3.0.0)
Requires-Dist: jupyter (>=1.0,<2.0)
Requires-Dist: numpy (>=1.16)
Requires-Dist: pandas (>=0.24.0)
Requires-Dist: scikit-learn (>=0.21.2)
Project-URL: Repository, https://github.com/metriculous-ml/metriculous
